laby_bot/__init__.py
laby_bot/__main__.py
laby_bot/robot.py
laby_bot/solver.py
laby_bot-0.0.dist-info/LICENSE
laby_bot-0.0.dist-info/METADATA
laby_bot-0.0.dist-info/WHEEL
laby_bot-0.0.dist-info/top_level.txt
laby_bot-0.0.dist-info/RECORD
