Metadata-Version: 2.1
Name: laby_bot
Version: 0.0
Summary: A pure Python, text-interface clone and solver of the Laby game
Home-page: https://github.com/hosford42/LabyBot
Author: Aaron Hosford
Author-email: hosford42@gmail.com
License: UNKNOWN
Project-URL: Bug Tracker, https://github.com/hosford42/LabyBot/issues
Project-URL: Original Laby Game, https://github.com/sgimenez/laby
Platform: UNKNOWN
Classifier: Programming Language :: Python :: 3 :: Only
Classifier: License :: OSI Approved :: MIT License
Classifier: Operating System :: OS Independent
Classifier: Topic :: Scientific/Engineering :: Artificial Intelligence
Requires-Python: >=3.8
License-File: LICENSE
